gym_ur/__init__.py
gym_ur/envs/__init__.py
gym_ur/envs/ur_Env.py
gym_ur/envs/utils.py
hjj_ur-0.0.1.dist-info/METADATA
hjj_ur-0.0.1.dist-info/WHEEL
hjj_ur-0.0.1.dist-info/top_level.txt
hjj_ur-0.0.1.dist-info/RECORD
