Metadata-Version: 2.1
Name: hjj-ur
Version: 0.0.1
Summary: An OpenAI Gym Env for Ur
Requires-Dist: gym
